{
  "BTC/USDT": {
    "direction": "FLAT",
    "entry": null,
    "strength": 0,
    "updated": "2026-06-27 17:54"
  },
  "ETH/USDT": {
    "direction": "FLAT",
    "entry": null,
    "strength": 0,
    "updated": "2026-06-27 19:02"
  },
  "BNB/USDT": {
    "direction": "SHORT",
    "entry": 562.24,
    "strength": 1,
    "updated": "2026-06-27 19:02"
  },
  "XRP/USDT": {
    "direction": "FLAT",
    "entry": null,
    "strength": 0,
    "updated": "2026-06-26 19:14"
  },
  "ADA/USDT": {
    "direction": "SHORT",
    "entry": 0.1453,
    "strength": 1,
    "updated": "2026-06-27 20:36"
  },
  "DOT/USDT": {
    "direction": "SHORT",
    "entry": 0.829,
    "strength": 1,
    "updated": "2026-06-27 20:36"
  },
  "LINK/USDT": {
    "direction": "FLAT",
    "entry": null,
    "strength": 0,
    "updated": "2026-06-27 19:02"
  },
  "NEAR/USDT": {
    "direction": "FLAT",
    "entry": null,
    "strength": 0,
    "updated": "2026-06-27 15:46"
  },
  "UNI/USDT": {
    "direction": "FLAT",
    "entry": null,
    "strength": 0,
    "updated": "2026-06-27 19:02"
  },
  "SOL/USDT": {
    "direction": "FLAT",
    "entry": null,
    "strength": 0,
    "updated": "2026-06-27 20:36"
  },
  "DOGE/USDT": {
    "direction": "SHORT",
    "entry": 0.07476,
    "strength": 1,
    "updated": "2026-06-27 20:36"
  },
  "BCH/USDT": {
    "direction": "FLAT",
    "entry": null,
    "strength": 0,
    "updated": "2026-06-27 17:54"
  },
  "TRX/USDT": {
    "direction": "FLAT",
    "entry": null,
    "strength": 0,
    "updated": "2026-06-27 20:36"
  },
  "AVAX/USDT": {
    "direction": "SHORT",
    "entry": 6.431,
    "strength": 1,
    "updated": "2026-06-27 20:36"
  },
  "ATOM/USDT": {
    "direction": "SHORT",
    "entry": 1.571,
    "strength": 1,
    "updated": "2026-06-27 20:36"
  },
  "LTC/USDT": {
    "direction": "FLAT",
    "entry": null,
    "strength": 0,
    "updated": "2026-06-27 15:46"
  }
}