{
  "BTC/USDT": {
    "direction": "FLAT",
    "entry": null,
    "strength": 0,
    "updated": "2026-06-24 19:08"
  },
  "ETH/USDT": {
    "direction": "FLAT",
    "entry": null,
    "strength": 0,
    "updated": "2026-06-24 19:08"
  },
  "BNB/USDT": {
    "direction": "FLAT",
    "entry": null,
    "strength": 0,
    "updated": "2026-06-24 19:08"
  },
  "XRP/USDT": {
    "direction": "FLAT",
    "entry": null,
    "strength": 0,
    "updated": "2026-06-24 15:16"
  },
  "ADA/USDT": {
    "direction": "FLAT",
    "entry": null,
    "strength": 0,
    "updated": "2026-06-24 19:08"
  },
  "DOT/USDT": {
    "direction": "SHORT",
    "entry": 0.855,
    "strength": 1,
    "updated": "2026-06-24 17:25"
  },
  "LINK/USDT": {
    "direction": "FLAT",
    "entry": null,
    "strength": 0,
    "updated": "2026-06-24 19:08"
  },
  "NEAR/USDT": {
    "direction": "SHORT",
    "entry": 1.887,
    "strength": 1,
    "updated": "2026-06-24 17:25"
  },
  "UNI/USDT": {
    "direction": "FLAT",
    "entry": null,
    "strength": 0,
    "updated": "2026-06-23 01:28"
  },
  "SOL/USDT": {
    "direction": "SHORT",
    "entry": 66.52,
    "strength": 1,
    "updated": "2026-06-24 17:25"
  },
  "DOGE/USDT": {
    "direction": "FLAT",
    "entry": null,
    "strength": 0,
    "updated": "2026-06-24 19:08"
  },
  "BCH/USDT": {
    "direction": "SHORT",
    "entry": 182.3,
    "strength": 1,
    "updated": "2026-06-24 17:25"
  },
  "TRX/USDT": {
    "direction": "FLAT",
    "entry": null,
    "strength": 0,
    "updated": "2026-06-24 19:08"
  },
  "AVAX/USDT": {
    "direction": "FLAT",
    "entry": null,
    "strength": 0,
    "updated": "2026-06-24 19:08"
  },
  "ATOM/USDT": {
    "direction": "SHORT",
    "entry": 1.626,
    "strength": 1,
    "updated": "2026-06-24 19:08"
  },
  "LTC/USDT": {
    "direction": "FLAT",
    "entry": null,
    "strength": 0,
    "updated": "2026-06-24 19:08"
  }
}